{"id": "1007460", "name": "Livestock-production-index"}
{"id": "1000030", "name": "GDP"}
{"id": "1015800", "name": "Expenditures-for-passenger-transport-items"}
{"id": "1000010", "name": "Global-competitiveness-index"}
{"id": "1008580", "name": "Forest-area-as-a-share-of-land-area"}
{"id": "1000720", "name": "Government-gross-debt-as-a-share-of-GDP"}
{"id": "1001350", "name": "Population-aged-65-years-and-above"}
{"id": "1013970", "name": "Poverty-rate-at-dollar19-a-day"}
{"id": "1010510", "name": "Child-mortality-rate"}
{"id": "1000500", "name": "Unemployment-rate"}
{"id": "1008480", "name": "Water-productivity"}
{"id": "1000700", "name": "Population"}
{"id": "1000220", "name": "Precipitation"}
{"id": "1012110", "name": "Diesel-price"}
{"id": "1008310", "name": "Energy-imports"}
{"id": "1006120", "name": "Education-expenditure"}
{"id": "1000000", "name": "Merchandise-exports"}
{"id": "1007430", "name": "Fertilizer-consumption"}
{"id": "1000040", "name": "Homicides-by-firearm-rate"}
{"id": "1015840", "name": "Tourism-receipts-as-a-share-of-exports"}
{"id": "1000310", "name": "Number-of-undernourished-people"}
{"id": "1000480", "name": "Fertility-rate"}
{"id": "1000030", "name": "CO2-emissions"}
{"id": "1000060", "name": "Military-expenditure-as-a-share-of-GDP"}
{"id": "1000030", "name": "Private-car-theft-rate"}
{"id": "1000600", "name": "Urban-population"}
{"id": "1033920", "name": "Duration-of-secondary-education"}
{"id": "1000180", "name": "GDP-per-capita"}
{"id": "1014990", "name": "Food-imports"}
{"id": "1000300", "name": "Renewable-water-resources-per-capita"}
{"id": "1000270", "name": "Volume-of-groundwater-produced"}
{"id": "1000010", "name": "Number-of-homicides"}
{"id": "1000050", "name": "Robbery-rate"}
{"id": "1008600", "name": "Land-area"}
{"id": "1000000", "name": "Property-rights-index"}
{"id": "1009860", "name": "Health-expenditure-as-a-share-of-GDP"}
{"id": "1011990", "name": "Number-of-scientific-journal-articles"}
{"id": "1000000", "name": "Press-freedom-index"}
{"id": "1000180", "name": "Goods-imports"}
{"id": "1000150", "name": "GDP-based-on-PPP"}
{"id": "1007410", "name": "Crop-production-index"}
{"id": "1015810", "name": "Expenditures-for-travel-items"}
{"id": "1000040", "name": "Corruption-perceptions-index"}
{"id": "1004740", "name": "Agriculture-value-added-per-worker"}
{"id": "1000080", "name": "Poverty-rate"}
{"id": "1000650", "name": "Female-population"}
{"id": "1011360", "name": "Maternal-mortality-ratio"}
{"id": "1013980", "name": "Poverty-rate-at-dollar32-a-day"}
{"id": "1011970", "name": "RandD-expenditure"}
{"id": "1000740", "name": "Current-account-balance"}
{"id": "1000260", "name": "Volume-of-surface-water-produced"}
{"id": "1000090", "name": "Rape-rate"}
{"id": "1000000", "name": "Homicide-rate"}
{"id": "1000390", "name": "Service-imports"}
{"id": "1000110", "name": "Birth-rate"}
{"id": "1000000", "name": "Political-rights-index"}
{"id": "1000010", "name": "Real-GDP-growth"}
{"id": "1015850", "name": "Tourism-receipts"}
{"id": "1000230", "name": "Precipitation-volume"}
{"id": "1015860", "name": "Receipts-for-passenger-transport-items"}
{"id": "1012120", "name": "Gasoline-price"}
{"id": "1008320", "name": "Alternative-and-nuclear-energy-use"}
{"id": "1007390", "name": "Cereal-production"}
{"id": "1011030", "name": "Population-growth-rate"}
{"id": "1011090", "name": "Population-aged-0-14-years"}
{"id": "1007440", "name": "Food-production-index"}
{"id": "1000040", "name": "CO2-emissions-per-capita"}
{"id": "1000600", "name": "International-reserves"}
{"id": "1016020", "name": "Arms-exports"}
{"id": "1000000", "name": "Index-of-economic-freedom"}
{"id": "1014950", "name": "Fuel-imports"}
{"id": "1000540", "name": "Dependency-ratio"}
{"id": "1000050", "name": "Motor-vehicle-theft-rate"}
{"id": "1010320", "name": "Life-expectancy"}
{"id": "1035050", "name": "Pupil-teacher-ratio-in-primary-education"}
{"id": "1011980", "name": "Number-of-researchers-in-RandD"}
{"id": "1011960", "name": "Number-of-patent-applications"}
{"id": "1012720", "name": "Employment-to-population-ratio"}
{"id": "1000030", "name": "Number-of-homicides-by-firearm"}
{"id": "1000010", "name": "Prosperity-index"}
{"id": "1008510", "name": "Agricultural-land-area"}
{"id": "1000300", "name": "Internal-renewable-water-resources-per-capita"}
{"id": "1000750", "name": "Current-account-balance-as-a-share-of-GDP"}
{"id": "1009870", "name": "Health-expenditure-per-capita"}
{"id": "1013840", "name": "GINI-index"}
{"id": "1000010", "name": "Merchandise-imports"}
{"id": "1000010", "name": "Civil-liberties-index"}
{"id": "1000010", "name": "Dietary-energy-supply-adequacy"}
{"id": "1000240", "name": "Rainfall-index"}
{"id": "1008330", "name": "Fossil-fuel-energy-consumption"}
{"id": "1001310", "name": "Population-aged-15-64-years"}
{"id": "1016040", "name": "Arms-imports"}
{"id": "1007570", "name": "Population-density"}
{"id": "1015870", "name": "Receipts-for-travel-items"}
{"id": "1012050", "name": "Air-transport-freight"}
{"id": "1000070", "name": "Burglary-and-housebreaking-rate"}
{"id": "1000050", "name": "CO2-emissions-intensity"}
{"id": "1008430", "name": "Freshwater-withdrawals"}
{"id": "1000000", "name": "Share-of-homicides-by-firearm"}
{"id": "1015820", "name": "Number-of-arrivals"}
{"id": "1000010", "name": "Happiness"}
{"id": "1008500", "name": "Agricultural-land-as-a-share-of-land-area"}
{"id": "1012140", "name": "Length-of-rail-lines"}
{"id": "1015830", "name": "Number-of-departures"}
{"id": "1013880", "name": "Income-share-held-by-lowest-10percent"}
{"id": "1012060", "name": "Number-of-air-passengers-carried"}
{"id": "1001230", "name": "Quantity-of-municipal-waste-collected"}
{"id": "1011910", "name": "High-technology-exports"}
{"id": "1000000", "name": "Primary-energy-production"}
{"id": "1007400", "name": "Cereal-yield"}
{"id": "1000310", "name": "Exports"}
{"id": "1000100", "name": "Share-of-households-with-Internet"}
{"id": "1015790", "name": "Tourism-expenditures"}
{"id": "1013860", "name": "Income-share-held-by-highest-10percent"}
{"id": "1000400", "name": "Road-density"}
{"id": "1000010", "name": "Human-development-index"}
{"id": "1011900", "name": "High-technology-exports-as-a-share-of-exports"}
{"id": "1007450", "name": "Land-under-cereal-production"}
{"id": "1012150", "name": "Volume-of-goods-transported-by-railways"}
{"id": "1000150", "name": "Primary-energy-consumption"}
{"id": "1000110", "name": "Goods-exports"}
{"id": "1015780", "name": "Tourism-expenditures-as-a-share-of-imports"}
{"id": "1010760", "name": "Prevalence-of-undernourishment"}
{"id": "1000020", "name": "Ease-of-doing-business-index"}
{"id": "1011860", "name": "Number-of-mobile-cellular-subscriptions"}
{"id": "1000020", "name": "Share-of-the-Internet-users"}
{"id": "1007360", "name": "Number-of-tractors"}
{"id": "1000320", "name": "Imports"}
{"id": "1012170", "name": "Number-of-passengers-carried-by-railways"}
{"id": "1008150", "name": "Energy-intensity"}
{"id": "1000250", "name": "Service-exports"}
{"id": "1000070", "name": "Military-expenditure"}
{"id": "1031780", "name": "Primary-enrollment"}
{"id": "1014750", "name": "Food-exports"}
{"id": "1010480", "name": "Neonatal-mortality-rate"}
{"id": "1000160", "name": "GDP-per-capita-based-on-PPP"}
{"id": "1014710", "name": "Fuel-exports"}
{"id": "1028100", "name": "Duration-of-primary-education"}
{"id": "1010450", "name": "Infant-mortality-rate"}
{"id": "1000310", "name": "Inflation-rate"}
{"id": "1000010", "name": "Burglary-rate"}
{"id": "1000140", "name": "Death-rate"}
{"id": "1035060", "name": "Pupil-teacher-ratio-in-secondary-education"}
{"id": "1011560", "name": "Incidence-of-tuberculosis"}
{"id": "1003130", "name": "Female-obesity-prevalence"}
{"id": "1003140", "name": "Male-obesity-prevalence"}
{"id": "1000010", "name": "Assault-rate"}
